sc8prx/__init__.py
sc8prx/ffmpeg.py
sc8prx/mpl.py
sc8prx/pil.py
sc8prx-3.0.4.dist-info/LICENSE.txt
sc8prx-3.0.4.dist-info/METADATA
sc8prx-3.0.4.dist-info/WHEEL
sc8prx-3.0.4.dist-info/top_level.txt
sc8prx-3.0.4.dist-info/RECORD
