Metadata-Version: 2.1
Name: sc8prx
Version: 3.0.4
Summary: Extra features for sc8pr 3
Home-page: https://dmaccarthy.github.io/sc8pr3/?sc8prx
Author: D.G. MacCarthy
Author-email: sc8pr.py@gmail.com
License: GPLv3
Keywords: graphics animation sprite gui robotics pygame educational
Classifier: Development Status :: 5 - Production/Stable
Classifier: Intended Audience :: Developers
Classifier: Intended Audience :: Education
Classifier: License :: OSI Approved :: GNU General Public License v3 (GPLv3)
Classifier: Programming Language :: Python :: 3
Classifier: Topic :: Software Development :: Libraries :: pygame
Classifier: Topic :: Multimedia :: Graphics
Classifier: Topic :: Education
Classifier: Topic :: Games/Entertainment
Requires-Python: >=3.7
License-File: LICENSE.txt
Requires-Dist: sc8pr ==3.0.4
Requires-Dist: imageio <3,>=2.8
Requires-Dist: imageio-ffmpeg <1,>=0.4
Requires-Dist: numpy <2,>=1.20
Requires-Dist: matplotlib <4,>=3.0
Requires-Dist: pillow <10,>=9.0
